server.py
mseep_elastic_semantic_search_mcp_server-0.1.4.dist-info/METADATA
mseep_elastic_semantic_search_mcp_server-0.1.4.dist-info/WHEEL
mseep_elastic_semantic_search_mcp_server-0.1.4.dist-info/entry_points.txt
mseep_elastic_semantic_search_mcp_server-0.1.4.dist-info/top_level.txt
mseep_elastic_semantic_search_mcp_server-0.1.4.dist-info/RECORD
