Metadata-Version: 2.4
Name: mseep-elastic-semantic-search-mcp-server
Version: 0.1.4
Summary: Add your description here
Author-email: mseep <support@skydeck.ai>
Requires-Python: >=3.13
Requires-Dist: elasticsearch>=8.17.2
Requires-Dist: mcp>=1.3.0
